yieldfrom.py
yield_from_as_an_iterator-1.2.0.dist-info/LICENSE
yield_from_as_an_iterator-1.2.0.dist-info/METADATA
yield_from_as_an_iterator-1.2.0.dist-info/WHEEL
yield_from_as_an_iterator-1.2.0.dist-info/top_level.txt
yield_from_as_an_iterator-1.2.0.dist-info/RECORD
