Metadata-Version: 2.1
Name: yield-from-as-an-iterator
Version: 1.2.0
Summary: A robust implementation of ``yield from`` behavior.
Home-page: https://github.com/mentalisttraceur/python-yieldfrom
Author: Alexander Kozhevnikov
Author-email: mentalisttraceur@gmail.com
License: 0BSD
Platform: UNKNOWN
Classifier: Development Status :: 5 - Production/Stable
Classifier: Programming Language :: Python :: 3
Classifier: Programming Language :: Python :: 2
Classifier: Operating System :: OS Independent
